ooresults/__init__.py
ooresults/_reader.py
ooresults/_server.py
ooresults/configuration.py
ooresults/reader.py
ooresults/server.py
ooresults/set_legacy_mode.py
ooresults/user.py
ooresults/handler/__init__.py
ooresults/handler/classes.py
ooresults/handler/clubs.py
ooresults/handler/competitors.py
ooresults/handler/courses.py
ooresults/handler/demo_reader.py
ooresults/handler/entries.py
ooresults/handler/events.py
ooresults/handler/results.py
ooresults/handler/root.py
ooresults/handler/series.py
ooresults/handler/si1.py
ooresults/handler/si2.py
ooresults/model/__init__.py
ooresults/model/build_results.py
ooresults/model/cached_result.py
ooresults/model/classes.py
ooresults/model/clubs.py
ooresults/model/competitors.py
ooresults/model/courses.py
ooresults/model/entries.py
ooresults/model/events.py
ooresults/model/results.py
ooresults/model/series.py
ooresults/otypes/__init__.py
ooresults/otypes/class_params.py
ooresults/otypes/class_type.py
ooresults/otypes/club_type.py
ooresults/otypes/competitor_type.py
ooresults/otypes/course_type.py
ooresults/otypes/entry_type.py
ooresults/otypes/event_type.py
ooresults/otypes/handicap.py
ooresults/otypes/result_type.py
ooresults/otypes/series_type.py
ooresults/otypes/start_type.py
ooresults/pdf/pdf.py
ooresults/pdf/result.py
ooresults/pdf/series.py
ooresults/pdf/splittimes.py
ooresults/pdf/fonts/Carlito-Bold.ttf
ooresults/pdf/fonts/Carlito-BoldItalic.ttf
ooresults/pdf/fonts/Carlito-Italic.ttf
ooresults/pdf/fonts/Carlito-Regular.ttf
ooresults/plugins/__init__.py
ooresults/plugins/iof_class_list.py
ooresults/plugins/iof_competitor_list.py
ooresults/plugins/iof_course_data.py
ooresults/plugins/iof_entry_list.py
ooresults/plugins/iof_result_list.py
ooresults/plugins/oe12.py
ooresults/plugins/oe2003.py
ooresults/plugins/imports/entries/__init__.py
ooresults/plugins/imports/entries/text.py
ooresults/repo/__init__.py
ooresults/repo/repo.py
ooresults/repo/sqlite_repo.py
ooresults/repo/update/__init__.py
ooresults-0.4.6.dist-info/licenses/LICENSE
ooresults-0.4.6.dist-info/METADATA
ooresults-0.4.6.dist-info/WHEEL
ooresults-0.4.6.dist-info/entry_points.txt
ooresults-0.4.6.dist-info/top_level.txt
ooresults-0.4.6.dist-info/RECORD
