Metadata-Version: 2.4
Name: ooresults
Version: 0.4.6
Summary: A software for the evaluation of the results of orienteering events
Author: Rainer Garus
License:                     GNU AFFERO GENERAL PUBLIC LICENSE
Project-URL: Repository, https://github.com/rgarus/ooresults
Project-URL: Documentation, https://ooresults.readthedocs.io/en/latest
Project-URL: Changelog, https://github.com/rgarus/ooresults/blob/main/CHANGELOG.rst
Keywords: orienteering,sportident
Classifier: Programming Language :: Python :: 3.9
Classifier: Programming Language :: Python :: 3.10
Classifier: Programming Language :: Python :: 3.11
Classifier: Programming Language :: Python :: 3.12
Classifier: Programming Language :: Python :: 3.13
Classifier: License :: OSI Approved :: GNU Affero General Public License v3 or later (AGPLv3+)
Classifier: Operating System :: OS Independent
Classifier: Intended Audience :: End Users/Desktop
Classifier: Development Status :: 4 - Beta
Requires-Python: >=3.9
License-File: LICENSE
Requires-Dist: bottle==0.13.4
Requires-Dist: case-converter
Requires-Dist: cheroot>=11.1.2
Requires-Dist: clevercsv
Requires-Dist: fastclasses-json
Requires-Dist: fpdf2==2.6.1
Requires-Dist: iso8601
Requires-Dist: jsonschema
Requires-Dist: lxml
Requires-Dist: Mako==1.3.10
Requires-Dist: pyOpenSSL
Requires-Dist: pyserial
Requires-Dist: requests
Requires-Dist: sireader
Requires-Dist: tzlocal
Requires-Dist: unidecode
Requires-Dist: websocket-client
Requires-Dist: websockets>=14.2
Provides-Extra: test
Requires-Dist: pytest>=8.3.3; extra == "test"
Requires-Dist: pytest-asyncio>=0.24.0; extra == "test"
Requires-Dist: selenium>=4.26.1; extra == "test"
Dynamic: license-file
